prompt_creator/__init__.py
prompt_creator/prompt_creator.py
prompt_creator-0.1.0.dist-info/METADATA
prompt_creator-0.1.0.dist-info/WHEEL
prompt_creator-0.1.0.dist-info/top_level.txt
prompt_creator-0.1.0.dist-info/RECORD
