Metadata-Version: 2.1
Name: prompt-creator
Version: 0.1.0
Summary: Create & send prompt
Author: DJ.cho
Author-email: dkrakepqlf54@gmail.com
Classifier: Programming Language :: Python :: 3
Classifier: License :: OSI Approved :: MIT License
Classifier: Operating System :: OS Independent
